common/__init__.py
common/decorators.py
common/descriptors.py
common/errors.py
common/metaclasses.py
common/utils.py
common/variables.py
log/__init__.py
log/server_log_config.py
server/__init__.py
server/add_user.py
server/config_window.py
server/core.py
server/database.py
server/main_window.py
server/remove_user.py
server/stat_window.py
message_server_korobanov-0.0.5.dist-info/METADATA
message_server_korobanov-0.0.5.dist-info/WHEEL
message_server_korobanov-0.0.5.dist-info/top_level.txt
message_server_korobanov-0.0.5.dist-info/RECORD
